README.md
setup.py
bomdia/__init__.py
bomdia.egg-info/PKG-INFO
bomdia.egg-info/SOURCES.txt
bomdia.egg-info/dependency_links.txt
bomdia.egg-info/top_level.txt